streamlit_mpl_svg/__init__.py
streamlit_mpl_svg/bar_chart_test.py
streamlit_mpl_svg/bar_group_chart_test.py
streamlit_mpl_svg/demo.py
streamlit_mpl_svg/line_plot_test.py
streamlit_mpl_svg-2.0.1.dist-info/LICENSE.txt
streamlit_mpl_svg-2.0.1.dist-info/METADATA
streamlit_mpl_svg-2.0.1.dist-info/WHEEL
streamlit_mpl_svg-2.0.1.dist-info/top_level.txt
streamlit_mpl_svg-2.0.1.dist-info/RECORD
