Metadata-Version: 2.1
Name: streamlit-mpl-svg
Version: 2.0.1
Summary: Reformat Matplotlib SVGs for easier access in Streamlit and customzation with CSS
Home-page: https://github.com/bouzidanas/streamlit-mpl-svg
Author: Anas Bouzid
Author-email: anasbouzid@gmail.com
Requires-Python: >=3.6
License-File: LICENSE.txt
Requires-Dist: streamlit (>=0.63)
Requires-Dist: matplotlib (>=3.2.1)
Requires-Dist: beautifulsoup4 (>=4.9.0)
Requires-Dist: lxml (>=4.5.0)
